LICENSE
README.md
setup.py
fortify_getorcreateapp/__init__.py
fortify_getorcreateapp/fortify_getorcreateapp.py
fortify_getorcreateapp.egg-info/PKG-INFO
fortify_getorcreateapp.egg-info/SOURCES.txt
fortify_getorcreateapp.egg-info/dependency_links.txt
fortify_getorcreateapp.egg-info/entry_points.txt
fortify_getorcreateapp.egg-info/requires.txt
fortify_getorcreateapp.egg-info/top_level.txt