Metadata-Version: 2.1
Name: fortify-getorcreateapp
Version: 0.2.15
Summary: Get a fortify application and version ids, create if they don't exist
Home-page: https://.trendmicro.com/cloudone-common/fortify-getorcreateapp
Author: Fabio Arciniegas
Author-email: fabio_arciniegas@trendmicro.com
Requires-Python: >=3.6
License-File: LICENSE
